odoo/addons/partner_phone_secondary/README.rst
odoo/addons/partner_phone_secondary/__init__.py
odoo/addons/partner_phone_secondary/__manifest__.py
odoo/addons/partner_phone_secondary/i18n/ca.po
odoo/addons/partner_phone_secondary/i18n/es.po
odoo/addons/partner_phone_secondary/i18n/it.po
odoo/addons/partner_phone_secondary/i18n/partner_phone_secondary.pot
odoo/addons/partner_phone_secondary/i18n/sv.po
odoo/addons/partner_phone_secondary/models/__init__.py
odoo/addons/partner_phone_secondary/models/res_partner.py
odoo/addons/partner_phone_secondary/readme/CONTRIBUTORS.rst
odoo/addons/partner_phone_secondary/readme/DESCRIPTION.rst
odoo/addons/partner_phone_secondary/static/description/icon.png
odoo/addons/partner_phone_secondary/static/description/index.html
odoo/addons/partner_phone_secondary/tests/__init__.py
odoo/addons/partner_phone_secondary/tests/test_partner_phone_secondary.py
odoo/addons/partner_phone_secondary/views/res_partner.xml
odoo14_addon_partner_phone_secondary-14.0.1.0.1.dev12.dist-info/METADATA
odoo14_addon_partner_phone_secondary-14.0.1.0.1.dev12.dist-info/WHEEL
odoo14_addon_partner_phone_secondary-14.0.1.0.1.dev12.dist-info/top_level.txt
odoo14_addon_partner_phone_secondary-14.0.1.0.1.dev12.dist-info/RECORD
